pytaon/__init__.py
pytaon/aabb.py
pytaon/body.py
pytaon/circle.py
pytaon/collision.py
pytaon/decorators.py
pytaon/mat2.py
pytaon/poly.py
pytaon/renderer.py
pytaon/segment.py
pytaon/space.py
pytaon/transform.py
pytaon/vec2d.py
pytaon-0.0.2b0.dist-info/LICENSE
pytaon-0.0.2b0.dist-info/WHEEL
pytaon-0.0.2b0.dist-info/METADATA
pytaon-0.0.2b0.dist-info/RECORD
